qtox
