Metadata-Version: 1.0
Name: qtox
Version: 0.0.6
Summary: Lets you re-run Tox commands faster and in parallel.
Home-page: UNKNOWN
Author: Tim Simpson
Author-email: UNKNOWN
License: MIT
Platform: UNKNOWN
